Metadata-Version: 1.0
Name: Film-analysis
Version: 1
Summary: This package analyzes data of films and directors
Home-page: UNKNOWN
Author: Sydorenko Valeriia
Author-email: jladan@uwaterloo.ca
License: MIT
Platform: UNKNOWN
